mysfire/__init__.py
mysfire/__init___test.py
mysfire/cloud_utils.py
mysfire/dataset.py
mysfire/lightning.py
mysfire/one_shot.py
mysfire/parser.py
mysfire/torch_utils.py
mysfire/vars_registry.py
mysfire/processors/__init__.py
mysfire/processors/_array_utils.py
mysfire/processors/_processor.py
mysfire/processors/base_types_processor.py
mysfire/processors/base_types_processor_test.py
mysfire/processors/h5py_processor.py
mysfire/processors/h5py_processor_test.py
mysfire/processors/image_processor.py
mysfire/processors/image_processor_test.py
mysfire/processors/npy_processor.py
mysfire/processors/npy_processor_test.py
mysfire/processors/pytorch_processor.py
mysfire/processors/pytorch_processor_test.py
mysfire/processors/video_processor.py
mysfire/processors/video_processor_test.py
mysfire/processors/nlp/__init__.py
mysfire/processors/nlp/tokenization_processor.py
mysfire-0.4.5.dist-info/LICENSE
mysfire-0.4.5.dist-info/METADATA
mysfire-0.4.5.dist-info/WHEEL
mysfire-0.4.5.dist-info/top_level.txt
mysfire-0.4.5.dist-info/RECORD
