Metadata-Version: 2.1
Name: mysfire
Version: 0.4.5
Summary: Fast (and opinionated) data loading for pytorch
Home-page: https://github.com/davidmchan/mysfire
Author: David Chan
Author-email: david@iridescent.io
License: MIT
Platform: UNKNOWN
Classifier: Programming Language :: Python :: 3
Classifier: License :: OSI Approved :: MIT License
Classifier: Operating System :: OS Independent
Classifier: Development Status :: 2 - Pre-Alpha
License-File: LICENSE
Requires-Dist: numpy (~=1.16)
Requires-Dist: torch (~=1.4)
Requires-Dist: sly (~=0.4)
Requires-Dist: pyarrow (~=6.0.1)
Requires-Dist: pytest (~=7.0)
Provides-Extra: all
Requires-Dist: h5py (~=3.0.0) ; extra == 'all'
Requires-Dist: tokenizers (~=0.11) ; extra == 'all'
Requires-Dist: torchvision (~=0.11) ; extra == 'all'
Requires-Dist: pillow (~=8.3.1) ; extra == 'all'
Requires-Dist: pytorchvideo (~=0.1.5) ; extra == 'all'
Requires-Dist: boto3 (~=1.16.9) ; extra == 'all'
Requires-Dist: filetype (~=1.0.10) ; extra == 'all'
Requires-Dist: google-cloud-storage (~=2.1.0) ; extra == 'all'
Requires-Dist: av (~=8.1.0) ; extra == 'all'
Requires-Dist: memory-tempfile (~=2.2.3) ; extra == 'all'
Requires-Dist: transformers (~=4.17.0) ; extra == 'all'
Provides-Extra: dev
Requires-Dist: h5py (~=3.0.0) ; extra == 'dev'
Requires-Dist: tokenizers (~=0.11) ; extra == 'dev'
Requires-Dist: torchvision (~=0.11) ; extra == 'dev'
Requires-Dist: pillow (~=8.3.1) ; extra == 'dev'
Requires-Dist: pytorchvideo (~=0.1.5) ; extra == 'dev'
Requires-Dist: boto3 (~=1.16.9) ; extra == 'dev'
Requires-Dist: filetype (~=1.0.10) ; extra == 'dev'
Requires-Dist: google-cloud-storage (~=2.1.0) ; extra == 'dev'
Requires-Dist: av (~=8.1.0) ; extra == 'dev'
Requires-Dist: memory-tempfile (~=2.2.3) ; extra == 'dev'
Requires-Dist: mypy (~=0.931) ; extra == 'dev'
Requires-Dist: flake8 (~=3.9.2) ; extra == 'dev'
Requires-Dist: black (~=21.7b0) ; extra == 'dev'
Requires-Dist: flake8-black (~=0.2.3) ; extra == 'dev'
Requires-Dist: isort (~=5.9.3) ; extra == 'dev'
Requires-Dist: commitizen (~=2.20.4) ; extra == 'dev'
Requires-Dist: pre-commit (~=2.13.0) ; extra == 'dev'
Provides-Extra: h5py
Requires-Dist: h5py (~=3.0.0) ; extra == 'h5py'
Provides-Extra: image
Requires-Dist: torchvision (~=0.11) ; extra == 'image'
Requires-Dist: pillow (~=8.3.1) ; extra == 'image'
Provides-Extra: nlp
Requires-Dist: tokenizers (~=0.11) ; extra == 'nlp'
Requires-Dist: transformers (~=4.17.0) ; extra == 'nlp'
Provides-Extra: s3
Requires-Dist: boto3 (~=1.16.9) ; extra == 's3'
Requires-Dist: filetype (~=1.0.10) ; extra == 's3'
Requires-Dist: google-cloud-storage (~=2.1.0) ; extra == 's3'
Provides-Extra: video
Requires-Dist: pytorchvideo (~=0.1.5) ; extra == 'video'
Requires-Dist: torchvision (~=0.11) ; extra == 'video'
Requires-Dist: pillow (~=8.3.1) ; extra == 'video'
Requires-Dist: av (~=8.1.0) ; extra == 'video'
